pymessagebus/__init__.py
pymessagebus/_commandbus.py
pymessagebus/_messagebus.py
pymessagebus/api.py
pymessagebus/default/__init__.py
pymessagebus/default/commandbus.py
pymessagebus/default/messagebus.py
pymessagebus/middleware/__init__.py
pymessagebus/middleware/logger.py
pymessagebus-1.2.3.dist-info/LICENSE
pymessagebus-1.2.3.dist-info/METADATA
pymessagebus-1.2.3.dist-info/WHEEL
pymessagebus-1.2.3.dist-info/top_level.txt
pymessagebus-1.2.3.dist-info/RECORD
