Metadata-Version: 2.1
Name: pymessagebus
Version: 1.2.3
Summary: A simple implementation of the MessageBus / CommandBus pattern
Home-page: https://github.com/DrBenton/pymessagebus
Author: Olivier Philippon
Author-email: olivier@rougemine.com
License: MIT
Keywords: CommandBus MessageBus CommandHandler DDD domain-driven-design design-pattern decoupling
Platform: UNKNOWN
Classifier: Development Status :: 5 - Production/Stable
Classifier: Intended Audience :: Developers
Classifier: License :: OSI Approved :: MIT License
Classifier: Operating System :: OS Independent
Classifier: Topic :: Software Development :: Libraries :: Python Modules
Classifier: Programming Language :: Python :: 3.6
Classifier: Programming Language :: Python :: 3.7
Classifier: Programming Language :: Python :: 3.8
Classifier: Programming Language :: Python :: 3.9
Requires-Python: >=3.6
